bazi_agent/__init__.py
bazi_agent/analyzer.py
bazi_agent/calendar.py
bazi_agent/config.py
bazi_agent/core.py
bazi_agent/dayun.py
bazi_agent/exceptions.py
bazi_agent/liunian.py
bazi_agent/llm.py
bazi_agent/output.py
bazi_agent/rules.py
bazi_agent/utils.py
bazi_agent-1.0.0.dist-info/LICENSE
bazi_agent-1.0.0.dist-info/METADATA
bazi_agent-1.0.0.dist-info/WHEEL
bazi_agent-1.0.0.dist-info/top_level.txt
bazi_agent-1.0.0.dist-info/RECORD
